dictionary/__init__.py
dictionary/dictionary.py
javid_homework_dictionary-2.0.1.dist-info/METADATA
javid_homework_dictionary-2.0.1.dist-info/WHEEL
javid_homework_dictionary-2.0.1.dist-info/top_level.txt
javid_homework_dictionary-2.0.1.dist-info/RECORD
